gravlearn/__init__.py
gravlearn/data_sampler.py
gravlearn/dataset.py
gravlearn/gravity_potential.py
gravlearn/losses.py
gravlearn/metrics.py
gravlearn/models.py
gravlearn/node_embedding_models.py
gravlearn/node_sampler.py
gravlearn/train.py
gravlearn/utils.py
gravlearn-0.0.10.dist-info/METADATA
gravlearn-0.0.10.dist-info/WHEEL
gravlearn-0.0.10.dist-info/top_level.txt
gravlearn-0.0.10.dist-info/RECORD
