Metadata-Version: 2.1
Name: gravlearn
Version: 0.0.10
Summary: gravlearn
Home-page: https://github.com/skojaku/gravlearn
Author: Sadamori Kojaku
License: MIT
Keywords: embedding
Classifier: Development Status :: 3 - Alpha
Classifier: Intended Audience :: Science/Research
Classifier: Topic :: Software Development
Classifier: License :: OSI Approved :: MIT License
Classifier: Programming Language :: Python :: 3.7
Classifier: Programming Language :: Python :: 3.8
